pysignald_async/__init__.py
pysignald_async-0.2.dist-info/WHEEL
pysignald_async-0.2.dist-info/METADATA
pysignald_async-0.2.dist-info/RECORD
